canvacord/__init__.py
canvacord/generators/__init__.py
canvacord/generators/aborted.py
canvacord/generators/affect.py
canvacord/generators/airpods.py
canvacord/generators/america.py
canvacord/generators/avatar.py
canvacord/generators/bed.py
canvacord/generators/communism.py
canvacord/generators/gay.py
canvacord/generators/hitler.py
canvacord/generators/jail.py
canvacord/generators/jokeoverhead.py
canvacord/generators/rankcard.py
canvacord/generators/spank.py
canvacord/generators/trigger.py
canvacord/generators/wanted.py
canvacord/generators/welcomecard.py
canvacord-3.4.9.dist-info/AUTHORS.rst
canvacord-3.4.9.dist-info/LICENSE
canvacord-3.4.9.dist-info/METADATA
canvacord-3.4.9.dist-info/WHEEL
canvacord-3.4.9.dist-info/top_level.txt
canvacord-3.4.9.dist-info/RECORD
