Metadata-Version: 2.1
Name: canvacord
Version: 3.4.9
Summary: A Python Version of Canvacord
Home-page: https://github.com/BlazenBoi/canvacord.py/issues
Author: Blazen
Author-email: contact@fireballbot.com
License: MIT
Project-URL: Discord Server, https://discord.com/invite/mPU3HybBs9
Project-URL: Bug Tracker, https://github.com/BlazenBoi/canvacord.py/issues
Project-URL: Source, https://github.com/BlazenBoi/canvacord
Keywords: canvacord,rankcard,image manipulation,meme,discord,discordpy,discord-py
Classifier: License :: OSI Approved :: MIT License
Classifier: Intended Audience :: Developers
Classifier: Natural Language :: English
Classifier: Operating System :: OS Independent
Classifier: Programming Language :: Python :: 3.6
Classifier: Programming Language :: Python :: 3.7
Classifier: Programming Language :: Python :: 3.8
Classifier: Programming Language :: Python :: 3.9
Classifier: Topic :: Internet
Classifier: Topic :: Software Development :: Libraries
Classifier: Topic :: Software Development :: Libraries :: Python Modules
Classifier: Topic :: Utilities
Requires-Python: >=3.6
License-File: LICENSE
License-File: AUTHORS.rst
Requires-Dist: setuptools >=42
Requires-Dist: wheel
Requires-Dist: pillow
Requires-Dist: discord
Requires-Dist: disnake
Requires-Dist: datetime
Requires-Dist: requests
Requires-Dist: colour
